odoo/addons/sale_promotion_discount_in_field/README.rst
odoo/addons/sale_promotion_discount_in_field/__init__.py
odoo/addons/sale_promotion_discount_in_field/__manifest__.py
odoo/addons/sale_promotion_discount_in_field/i18n/it.po
odoo/addons/sale_promotion_discount_in_field/i18n/sale_promotion_discount_in_field.pot
odoo/addons/sale_promotion_discount_in_field/models/__init__.py
odoo/addons/sale_promotion_discount_in_field/models/coupon_program.py
odoo/addons/sale_promotion_discount_in_field/models/coupon_reward.py
odoo/addons/sale_promotion_discount_in_field/models/sale_order.py
odoo/addons/sale_promotion_discount_in_field/readme/CONTRIBUTORS.rst
odoo/addons/sale_promotion_discount_in_field/readme/CREDITS.rst
odoo/addons/sale_promotion_discount_in_field/readme/DESCRIPTION.rst
odoo/addons/sale_promotion_discount_in_field/readme/ROADMAP.rst
odoo/addons/sale_promotion_discount_in_field/readme/USAGE.rst
odoo/addons/sale_promotion_discount_in_field/static/description/icon.png
odoo/addons/sale_promotion_discount_in_field/static/description/index.html
odoo/addons/sale_promotion_discount_in_field/tests/__init__.py
odoo/addons/sale_promotion_discount_in_field/tests/test_promotion_discount_in_field.py
odoo/addons/sale_promotion_discount_in_field/views/coupon_program_view.xml
odoo/addons/sale_promotion_discount_in_field/wizard/__init__.py
odoo/addons/sale_promotion_discount_in_field/wizard/sale_coupon_apply_code.py
odoo14_addon_sale_promotion_discount_in_field-14.0.1.1.0.dist-info/METADATA
odoo14_addon_sale_promotion_discount_in_field-14.0.1.1.0.dist-info/WHEEL
odoo14_addon_sale_promotion_discount_in_field-14.0.1.1.0.dist-info/top_level.txt
odoo14_addon_sale_promotion_discount_in_field-14.0.1.1.0.dist-info/RECORD
